patacrep/Rx.py
patacrep/__init__.py
patacrep/authors.py
patacrep/build.py
patacrep/encoding.py
patacrep/errors.py
patacrep/files.py
patacrep/index.py
patacrep/templates.py
patacrep/utils.py
patacrep/content/__init__.py
patacrep/content/addsongdir.py
patacrep/content/cd.py
patacrep/content/include.py
patacrep/content/section.py
patacrep/content/setcounter.py
patacrep/content/song.py
patacrep/content/songsection.py
patacrep/content/sort.py
patacrep/content/tex.py
patacrep/data/img/internet.png
patacrep/data/img/treble_a.png
patacrep/data/templates/songbook_model.yml
patacrep/data/templates/songbook/default.tex
patacrep/data/templates/songbook/layout.tex
patacrep/data/templates/songbook/patacrep.tex
patacrep/data/templates/songbook/songs.tex
patacrep/data/templates/songs/chordpro/chordpro/content_chord
patacrep/data/templates/songs/chordpro/chordpro/content_chordlist
patacrep/data/templates/songs/chordpro/chordpro/content_comment
patacrep/data/templates/songs/chordpro/chordpro/content_define
patacrep/data/templates/songs/chordpro/chordpro/content_echo
patacrep/data/templates/songs/chordpro/chordpro/content_endofline
patacrep/data/templates/songs/chordpro/chordpro/content_error
patacrep/data/templates/songs/chordpro/chordpro/content_guitar_comment
patacrep/data/templates/songs/chordpro/chordpro/content_image
patacrep/data/templates/songs/chordpro/chordpro/content_line
patacrep/data/templates/songs/chordpro/chordpro/content_meta
patacrep/data/templates/songs/chordpro/chordpro/content_newline
patacrep/data/templates/songs/chordpro/chordpro/content_partition
patacrep/data/templates/songs/chordpro/chordpro/content_space
patacrep/data/templates/songs/chordpro/chordpro/content_tablature
patacrep/data/templates/songs/chordpro/chordpro/content_verse
patacrep/data/templates/songs/chordpro/chordpro/content_word
patacrep/data/templates/songs/chordpro/chordpro/song
patacrep/data/templates/songs/chordpro/chordpro/song_body
patacrep/data/templates/songs/chordpro/chordpro/song_header
patacrep-5.2.1.dist-info/LICENSE
patacrep-5.2.1.dist-info/METADATA
patacrep-5.2.1.dist-info/WHEEL
patacrep-5.2.1.dist-info/entry_points.txt
patacrep-5.2.1.dist-info/top_level.txt
patacrep-5.2.1.dist-info/RECORD
