Metadata-Version: 2.1
Name: patacrep
Version: 5.2.1
Summary: Songbook compilation chain
Home-page: https://github.com/patacrep/patacrep
Author: The Songbook team
Author-email: crep@team-on-fire.com
License: GPLv2 or any later version
Platform: GNU/Linux
Platform: Windows
Platform: MacOsX
Classifier: Environment :: Console
Classifier: License :: OSI Approved :: GNU General Public License v2 or later (GPLv2+)
Classifier: Natural Language :: English
Classifier: Operating System :: POSIX :: Linux
Classifier: Operating System :: Microsoft :: Windows
Classifier: Operating System :: MacOS :: MacOS X
Classifier: Programming Language :: Python :: 3.3
Classifier: Programming Language :: Python :: 3.4
Classifier: Topic :: Utilities
License-File: LICENSE
Requires-Dist: argdispatch
Requires-Dist: jinja2
Requires-Dist: ply
Requires-Dist: pyyaml
Requires-Dist: unidecode
